group_theory/__init__.py
group_theory/group_element.py
group_theory/group_utils.py
group_theory/groups.py
group_theory/permutation.py
group_theory/symbolic.py
group_theory/utils.py
group_theory-0.0.3a0.dist-info/METADATA
group_theory-0.0.3a0.dist-info/WHEEL
group_theory-0.0.3a0.dist-info/licenses/LICENSE
group_theory-0.0.3a0.dist-info/RECORD
