Metadata-Version: 2.4
Name: group_theory
Version: 0.0.3a0
Summary: A Python package for performing group theory computations.
Project-URL: Homepage, https://github.com/JacksonKaunismaa/group_theory
Project-URL: Issues, https://github.com/JacksonKaunismaa/group_theory/issues
Author-email: Jackson Kaunismaa <jackkaunis@protonmail.com>
License:                     GNU GENERAL PUBLIC LICENSE
License-File: LICENSE
Keywords: algebra,group theory,mathematics
Classifier: Development Status :: 3 - Alpha
Classifier: Intended Audience :: Developers
Classifier: License :: OSI Approved :: GNU General Public License v3 (GPLv3)
Classifier: Programming Language :: Python :: 3
Classifier: Programming Language :: Python :: 3.6
Classifier: Programming Language :: Python :: 3.7
Classifier: Programming Language :: Python :: 3.8
Classifier: Programming Language :: Python :: 3.9
Classifier: Programming Language :: Python :: 3.10
Classifier: Topic :: Scientific/Engineering :: Mathematics
Classifier: Typing :: Typed
Requires-Python: >=3.6
Requires-Dist: tqdm
